fetchtool/__init__.py
fetchtool/abstract_fetch.py
fetchtool/exceptions.py
fetchtool/fetch_assemblies.py
fetchtool/fetch_reads.py
fetch_tool-1.0.4.dist-info/LICENSE
fetch_tool-1.0.4.dist-info/METADATA
fetch_tool-1.0.4.dist-info/WHEEL
fetch_tool-1.0.4.dist-info/entry_points.txt
fetch_tool-1.0.4.dist-info/top_level.txt
fetch_tool-1.0.4.dist-info/RECORD
