Metadata-Version: 2.1
Name: fetch-tool
Version: 1.0.4
Summary: Utility to fetch public and private RAW read and assembly files from the ENA
Author-email: MGnify team <metagenomics-help@ebi.ac.uk>
License: Apache Software License 2.0
Keywords: bioinformatics,tool,metagenomics
Classifier: Programming Language :: Python :: 3.8
Classifier: Programming Language :: Python :: 3.9
Classifier: Programming Language :: Python :: 3.10
Classifier: Development Status :: 5 - Production/Stable
Classifier: Intended Audience :: Science/Research
Classifier: Topic :: Scientific/Engineering :: Bio-Informatics
Classifier: License :: OSI Approved :: Apache Software License
Classifier: Operating System :: OS Independent
Requires-Python: >=3.8
License-File: LICENSE
Requires-Dist: requests ==2.32.3
Requires-Dist: flufl.lock ==8.1.0
Requires-Dist: pandas ==2.2.2
Requires-Dist: boto3 ==1.34.134
Requires-Dist: tenacity ==8.4.2
Provides-Extra: dev
Requires-Dist: pre-commit ==3.3.3 ; extra == 'dev'
Requires-Dist: black ==23.7.0 ; extra == 'dev'
Requires-Dist: ruff ==v0.0.286 ; extra == 'dev'
Requires-Dist: isort ==5.12.0 ; extra == 'dev'
Requires-Dist: bump-my-version ==0.9.2 ; extra == 'dev'
Provides-Extra: test
Requires-Dist: pytest ==7.1.2 ; extra == 'test'
Requires-Dist: pytest-cov ==3.0.0 ; extra == 'test'
Requires-Dist: flaky ==3.7.0 ; extra == 'test'
